dbus_objects/__init__.py
dbus_objects/object.py
dbus_objects/signature.py
dbus_objects/types.py
dbus_objects/integration/__init__.py
dbus_objects/integration/jeepney.py
dbus_objects/integration/jeepney_trio.py
dbus_objects-0.0.2.dist-info/LICENSE
dbus_objects-0.0.2.dist-info/METADATA
dbus_objects-0.0.2.dist-info/WHEEL
dbus_objects-0.0.2.dist-info/top_level.txt
dbus_objects-0.0.2.dist-info/RECORD
