Metadata-Version: 2.1
Name: dbus-objects
Version: 0.0.2
Summary: UNKNOWN
Home-page: UNKNOWN
Author: Filipe Laíns
Author-email: lains@archlinux.org
License: MIT
Project-URL: homepage, https://github.com/FFY00/dbus-objects
Project-URL: changelog, https://github.com/FFY00/dbus-objects/blob/master/CHANGELOG.rst
Platform: UNKNOWN
Classifier: License :: OSI Approved :: MIT License
Classifier: Programming Language :: Python :: 3.7
Classifier: Programming Language :: Python :: 3.8
Classifier: Development Status :: 4 - Beta
Classifier: Intended Audience :: Developers
Requires-Python: >=3.7
Requires-Dist: treelib
Requires-Dist: typing-extensions ; python_version < "3.9"
Provides-Extra: docs
Requires-Dist: furo ; extra == 'docs'
Requires-Dist: sphinx (==3.*) ; extra == 'docs'
Requires-Dist: sphinx-autodoc-typehints ; extra == 'docs'
Requires-Dist: jeepney ; extra == 'docs'
Provides-Extra: jeepney
Requires-Dist: jeepney (>=0.5) ; extra == 'jeepney'
Provides-Extra: test
Requires-Dist: pytest ; extra == 'test'
Requires-Dist: pytest-subtests ; extra == 'test'
Requires-Dist: pytest-cov ; extra == 'test'
Requires-Dist: pytest-trio ; extra == 'test'
Requires-Dist: jeepney (>=0.5) ; extra == 'test'
Requires-Dist: trio ; extra == 'test'
Requires-Dist: xmldiff ; extra == 'test'
